{
  "required": true,
  "minVersion": "0.8",
  "package": "net.yukulab.pointactivity.mixin",
  "compatibilityLevel": "JAVA_17",
  "client": [
    "client.MixinInGameHud",
    "client.MixinMinecraftClient"
  ],
  "server": [
    "server.MixinClientConnection",
    "server.MixinCraftingResultSlot",
    "server.MixinLivingEntity",
    "server.MixinMinecraftDedicatedServer",
    "server.MixinPlayerEntity",
    "server.MixinPlayerManager",
    "server.MixinServerPlayerEntity"
  ],
  "injectors": {
    "defaultRequire": 1
  }
}
